lightweb4py/__init__.py
lightweb4py/framework.py
lightweb4py/logger.py
lightweb4py/persistence.py
lightweb4py/persistence_sqlite.py
lightweb4py/request.py
lightweb4py/response.py
lightweb4py/settings.py
lightweb4py/singleton.py
lightweb4py/urls.py
lightweb4py/views.py
lightweb4py/demo/app.py
lightweb4py/demo/app_student.py
lightweb4py/demo/category.py
lightweb4py/demo/course.py
lightweb4py/demo/element_edit.py
lightweb4py/demo/feedback.py
lightweb4py/demo/logs.py
lightweb4py/demo/miscellaneous.py
lightweb4py/demo/settings.py
lightweb4py/demo/student.py
lightweb4py/demo/urls.py
lightweb4py/demo/views.py
lightweb4py/demo/contact_messages/2022-05-01T21-05-19_feo@sao.la
lightweb4py/demo/contact_messages/2022-05-01T21-46-24_feo@sao.la
lightweb4py/demo/contact_messages/2022-05-01T23-48-00_feo@sao.la
lightweb4py/demo/contact_messages/2022-05-06T13-51-40_feo@sao.la
lightweb4py/demo/database/categories.json
lightweb4py/demo/database/courses.json
lightweb4py/demo/database/database.db
lightweb4py/demo/database/feedback.json
lightweb4py/demo/database/students.json
lightweb4py/demo/docs/README.md
lightweb4py/demo/templates/contact.html
lightweb4py/demo/templates/contact_success.html
lightweb4py/demo/templates/element_edit.html
lightweb4py/demo/templates/element_edit_category_field.html
lightweb4py/demo/templates/element_edit_course_field.html
lightweb4py/demo/templates/element_edit_name_field.html
lightweb4py/demo/templates/element_edit_person_fields.html
lightweb4py/demo/templates/feedback.html
lightweb4py/demo/templates/index.html
lightweb4py/demo/templates/left_sidebar.html
lightweb4py/docs/README.md
lightweb4py/docs/examples/app_test_cbv.py
lightweb4py/docs/examples/app_test_logger.py
lightweb4py/docs/examples/app_test_minimal.py
lightweb4py/docs/examples/app_test_persistence.py
lightweb4py/docs/examples/templates/contact.html
lightweb4py/docs/examples/templates/index.html
lightweb4py/templates/admin.html
lightweb4py/templates/admin_parameter.html
lightweb4py-0.1.0b1.dist-info/LICENSE
lightweb4py-0.1.0b1.dist-info/METADATA
lightweb4py-0.1.0b1.dist-info/WHEEL
lightweb4py-0.1.0b1.dist-info/top_level.txt
lightweb4py-0.1.0b1.dist-info/RECORD
