Metadata-Version: 2.1
Name: lightweb4py
Version: 0.1.0b1
Summary: A lightweight web framework with Router, CBV, ORM and Logger
Home-page: https://github.com/nekidoz/lightweb4py
Author: Nikita Vaysberg
Author-email: nekidoz@yandex.ru
License: UNKNOWN
Project-URL: Source, https://github.com/nekidoz/lightweb4py
Project-URL: Bug Tracker, https://github.com/nekidoz/lightweb4py/issues
Keywords: development wsgi orm cbv logger
Platform: UNKNOWN
Classifier: Programming Language :: Python :: 3
Classifier: License :: OSI Approved :: MIT License
Classifier: Operating System :: OS Independent
Classifier: Development Status :: 4 - Beta
Classifier: Intended Audience :: Developers
Classifier: Intended Audience :: Education
Classifier: Intended Audience :: Information Technology
Classifier: Topic :: Internet :: WWW/HTTP :: WSGI
Classifier: Topic :: Software Development :: Libraries :: Application Frameworks
Classifier: Topic :: Software Development :: Libraries :: Python Modules
Classifier: Topic :: Software Development :: User Interfaces
Classifier: Topic :: System :: Logging
Classifier: Topic :: Database
Requires-Python: >=3.7
License-File: LICENSE
Requires-Dist: requests (<3,>=2)
Requires-Dist: jinja2 (<4,>=3)
